{
  "components": [
    {
      "components": [
        {
          "name": "main",
          "style": {
            "width": "1823px"
          },
          "type": "content-container"
        }
      ],
      "name": "body1",
      "style": {
        "paddingBottom": "0",
        "paddingLeft": "0",
        "paddingRight": "0",
        "paddingTop": "0"
      },
      "type": "body"
    },
    {
      "components": [
        {
          "name": "label0",
          "style": {
            "backgroundColor": "#e6c54f",
            "color": "#3a474d",
            "fontSize": "10px",
            "fontWeight": "normal"
          },
          "text": "Header",
          "type": "label"
        }
      ],
      "name": "header0",
      "style": {
        "backgroundColor": "rgba(0, 0, 0, 0)",
        "height": "55px",
        "width": "40px"
      },
      "type": "header"
    }
  ],
  "events": {
    "load": [
      {
        "name": "onClickNavigateBack",
        "type": "set",
        "value": "() => {\n    if (this.dialogRef) {\n      this.dialogRef.close();\n    }\n    this._location.back();\n}"
      }
    ]
  },
  "name": "InventurErfassen"
}